.gitignore
.hgignore
.hgtags
.project
.pydevproject
COPYING
MANIFEST.in
README.rst
distribute_setup.py
milla.svg
setup.py
.settings/org.eclipse.core.resources.prefs
doc/Makefile
doc/advanced.rst
doc/changelog.rst
doc/conf.py
doc/getting-started.rst
doc/glossary.rst
doc/index.rst
doc/make.bat
doc/reference/app.rst
doc/reference/controllers.rst
doc/reference/index.rst
doc/reference/milla.rst
doc/reference/util.rst
doc/reference/vary.rst
doc/reference/auth/decorators.rst
doc/reference/auth/index.rst
doc/reference/auth/permissions.rst
doc/reference/dispatch/index.rst
doc/reference/dispatch/routing.rst
doc/reference/dispatch/traversal.rst
src/Milla.egg-info/PKG-INFO
src/Milla.egg-info/SOURCES.txt
src/Milla.egg-info/dependency_links.txt
src/Milla.egg-info/entry_points.txt
src/Milla.egg-info/requires.txt
src/Milla.egg-info/top_level.txt
src/milla/__init__.py
src/milla/app.py
src/milla/controllers.py
src/milla/milla.ico
src/milla/util.py
src/milla/vary.py
src/milla/auth/__init__.py
src/milla/auth/decorators.py
src/milla/auth/permissions.py
src/milla/dispatch/__init__.py
src/milla/dispatch/routing.py
src/milla/dispatch/traversal.py
test/__init__.py
test/test_app.py
test/test_auth.py
test/test_routing.py
test/test_traversal.py
test/test_vary.py