Metadata-Version: 1.1
Name: Milla
Version: 1.0
Summary: Lightweight WSGI framework for web applications
Home-page: http://bitbucket.org/AdmiralNemo/milla
Author: Dustin C. Hatch
Author-email: admiralnemo@gmail.com
License: APACHE-2
Platform: UNKNOWN
Classifier: Development Status :: 3 - Alpha
Classifier: Environment :: Web Environment
Classifier: Intended Audience :: Developers
Classifier: License :: OSI Approved :: Apache Software License
Classifier: Programming Language :: Python :: 2.6
Classifier: Programming Language :: Python :: 2.7
Classifier: Topic :: Internet :: WWW/HTTP :: WSGI :: Application
